[
    {
        "albumArt": "https://e.snmc.io/i/300/w/b5b87a8e67078af71f0b53d26a9bb539/8538705",
        "position": 1,
        "title": "For the First Time",
        "artist": "Black Country, New Road",
        "releaseDate": {
            "month": "February",
            "date": 5,
            "year": 2021
        },
        "avgRating": 3.75,
        "ratings": null,
        "reviews": 201,
        "primaryGenres": [
            "Post-Rock",
            "Experimental Rock",
            "Post-Punk"
        ],
        "secondaryGenres": [
            "Klezmer",
            "Art Punk",
            "Art Rock"
        ],
        "descriptors": [
            "anxious",
            "manic",
            "male vocals",
            "monologue",
            "suspenseful",
            "abstract",
            "introspective",
            "progressive",
            "passionate",
            "complex"
        ],
        "externalLinks": {
            "appleMusic": "https://geo.music.apple.com/us/album/for-the-first-time/1533822061?mt=1&app=music&at=10l59k&ct=10l59k",
            "bandcamp": "https://blackcountrynewroad.bandcamp.com/album/for-the-first-time",
            "soundcloud": "https://soundcloud.com/blackcountrynewroad/sets/for-the-first-time-972675155",
            "spotify": "https://open.spotify.com/album/2PfgptDcfJTFtoZIS3AukX"
        }
    },
    {
        "albumArt": "https://e.snmc.io/i/300/w/7de49c247392a74a8875a58482097e7c/8767991",
        "position": 2,
        "title": "Clamor",
        "artist": "Maria Arnal i Marcel Bagés",
        "releaseDate": {
            "month": "March",
            "date": 5,
            "year": 2021
        },
        "avgRating": 3.86,
        "ratings": 111,
        "reviews": 3,
        "primaryGenres": [
            "Art Pop",
            "Glitch Pop"
        ],
        "secondaryGenres": [
            "Avant-Folk",
            "IDM",
            "Folktronica",
            "Electroacoustic"
        ],
        "descriptors": [
            "female vocals",
            "space",
            "melodic",
            "progressive",
            "atmospheric",
            "passionate",
            "poetic",
            "eclectic",
            "ethereal",
            "complex"
        ],
        "externalLinks": {
            "appleMusic": "https://geo.music.apple.com/us/album/clamor/1550679176?mt=1&app=music&at=10l59k&ct=10l59k",
            "spotify": "https://open.spotify.com/album/56FfSg2yi8EnmoY8OB85Sw",
            "youtube": "https://www.youtube.com/watch?v=Ty2iW4k5ow8"
        }
    },
    {
        "albumArt": "https://e.snmc.io/i/300/w/c3450737eebbb08e9bdc381c7307d1e7/8752489",
        "position": 3,
        "title": "Imperative Imperceptible Impulse",
        "artist": "Ad Nauseam",
        "releaseDate": {
            "month": "February",
            "date": 12,
            "year": 2021
        },
        "avgRating": 3.72,
        "ratings": null,
        "reviews": 12,
        "primaryGenres": [
            "Technical Death Metal",
            "Avant-Garde Metal"
        ],
        "secondaryGenres": [
            "Progressive Metal"
        ],
        "descriptors": [
            "uncommon time signatures",
            "technical",
            "complex",
            "dissonant",
            "heavy",
            "aggressive",
            "avant-garde",
            "male vocals",
            "dark",
            "atmospheric"
        ],
        "externalLinks": {
            "bandcamp": "https://adnauseam-official.bandcamp.com/album/imperative-imperceptible-impulse-full-dynamic-range-dr11"
        }
    },
    {
        "albumArt": "https:",
        "position": 4,
        "title": "Carnage",
        "artist": "Nick Cave & Warren Ellis",
        "releaseDate": {
            "month": "February",
            "date": 25,
            "year": 2021
        },
        "avgRating": 3.66,
        "ratings": null,
        "reviews": 24,
        "primaryGenres": [
            "Chamber Pop",
            "Art Pop"
        ],
        "secondaryGenres": [
            "Ambient Pop"
        ],
        "descriptors": [
            "male vocals",
            "poetic",
            "atmospheric",
            "sparse",
            "melancholic",
            "longing",
            "calm",
            "sentimental",
            "passionate",
            "lonely"
        ],
        "externalLinks": {
            "appleMusic": "https://geo.music.apple.com/us/album/carnage/1552929712?mt=1&app=music&at=10l59k&ct=10l59k",
            "spotify": "https://open.spotify.com/album/6xWNh0mUOdEg77U1f6oojz"
        }
    },
    {
        "albumArt": "https:",
        "position": 5,
        "title": "Smiling With No Teeth",
        "artist": "Genesis Owusu",
        "releaseDate": {
            "month": "March",
            "date": 5,
            "year": 2021
        },
        "avgRating": 3.71,
        "ratings": 175,
        "reviews": 5,
        "primaryGenres": [
            "Neo-Soul"
        ],
        "secondaryGenres": [
            "Funk",
            "Conscious Hip Hop",
            "Post-Punk",
            "Alternative R&B",
            "Experimental Hip Hop",
            "Synth Punk"
        ],
        "descriptors": [
            "eclectic",
            "playful",
            "energetic",
            "male vocals",
            "optimistic",
            "political",
            "conscious",
            "introspective",
            "quirky",
            "rhythmic"
        ],
        "externalLinks": {
            "appleMusic": "https://geo.music.apple.com/us/album/smiling-with-no-teeth/1538031240?mt=1&app=music&at=10l59k&ct=10l59k",
            "soundcloud": "https://soundcloud.com/genesis-owusu/sets/smiling-with-no-teeth-1",
            "spotify": "https://open.spotify.com/album/7LI6T5cy6Et8RDZXCoCEtJ"
        }
    },
    {
        "albumArt": "https:",
        "position": 6,
        "title": "To See the Next Part of the Dream",
        "artist": "파란노을 [Parannoul]",
        "releaseDate": {
            "month": "February",
            "date": 23,
            "year": 2021
        },
        "avgRating": 3.75,
        "ratings": 71,
        "reviews": 12,
        "primaryGenres": [
            "Shoegaze",
            "Emo"
        ],
        "secondaryGenres": [
            "Noise Pop",
            "Post-Hardcore",
            "Post-Rock"
        ],
        "descriptors": [
            "introspective",
            "male vocals",
            "melancholic",
            "raw",
            "self-hatred",
            "noisy",
            "concept album",
            "cold",
            "alienation",
            "depressive"
        ],
        "externalLinks": {
            "bandcamp": "https://parannoul.bandcamp.com/album/to-see-the-next-part-of-the-dream",
            "youtube": "https://www.youtube.com/watch?v=tGaz4EJObiw"
        }
    },
    {
        "albumArt": "https:",
        "position": 7,
        "title": "Modern Grotesque",
        "artist": "Dreamwell",
        "releaseDate": {
            "month": "February",
            "date": 26,
            "year": 2021
        },
        "avgRating": 3.86,
        "ratings": 37,
        "reviews": 2,
        "primaryGenres": [
            "Screamo"
        ],
        "secondaryGenres": [
            "Post-Hardcore",
            "Post-Rock"
        ],
        "descriptors": [
            "chaotic",
            "introspective",
            "death",
            "passionate",
            "angry",
            "male vocals",
            "depressive",
            "melancholic",
            "anxious"
        ],
        "externalLinks": {
            "bandcamp": "https://dreamwell.bandcamp.com/album/modern-grotesque",
            "spotify": "https://open.spotify.com/album/5qyK35Ve2O7mxWbrsiWkm0"
        }
    },
    {
        "albumArt": "https:",
        "position": 8,
        "title": "Lifeblood",
        "artist": "Brand of Sacrifice",
        "releaseDate": {
            "month": "March",
            "date": 5,
            "year": 2021
        },
        "avgRating": 3.74,
        "ratings": 75,
        "reviews": 5,
        "primaryGenres": [
            "Deathcore",
            "Slam Death Metal"
        ],
        "secondaryGenres": [
            "Electronic",
            "Symphonic Metal"
        ],
        "descriptors": [
            "heavy",
            "energetic",
            "aggressive",
            "dense",
            "angry",
            "futuristic",
            "male vocals"
        ],
        "externalLinks": {
            "bandcamp": "https://brandofsacrifice.bandcamp.com/album/lifeblood",
            "spotify": "https://open.spotify.com/album/3qhaQQ83nKm4UpkHuiBu7R"
        }
    },
    {
        "albumArt": "https:",
        "position": 9,
        "title": "The Cyclic Reckoning",
        "artist": "Suffering Hour",
        "releaseDate": {
            "month": "February",
            "date": 19,
            "year": 2021
        },
        "avgRating": 3.59,
        "ratings": 639,
        "reviews": 2,
        "primaryGenres": [
            "Black Metal",
            "Death Metal"
        ],
        "secondaryGenres": [
            "Atmospheric Black Metal"
        ],
        "descriptors": [
            "dark",
            "male vocals",
            "dissonant",
            "heavy",
            "atmospheric",
            "aggressive",
            "sombre",
            "introspective",
            "cryptic",
            "raw"
        ],
        "externalLinks": {
            "appleMusic": "https://geo.music.apple.com/us/album/the-cyclic-reckoning/1540750997?mt=1&app=music&at=10l59k&ct=10l59k",
            "bandcamp": "https://sufferinghour.bandcamp.com/album/the-cyclic-reckoning",
            "spotify": "https://open.spotify.com/album/5ImYMM1y6WbfxT1ONknkdX",
            "youtube": "https://www.youtube.com/watch?v=TDHI1MY-u8Q"
        }
    },
    {
        "albumArt": "https:",
        "position": 10,
        "title": "Inside.Outside.Inside.Outside.",
        "artist": "Steel Tipped Dove",
        "releaseDate": {
            "month": "January",
            "date": 23,
            "year": 2021
        },
        "avgRating": 3.98,
        "ratings": 15,
        "reviews": 4,
        "primaryGenres": [
            "Instrumental Hip Hop",
            "Experimental Hip Hop",
            "Downtempo"
        ],
        "secondaryGenres": [
            "Neo-Psychedelia",
            "Nature Recordings",
            "Chipmunk Soul"
        ],
        "descriptors": [
            "lo-fi",
            "sampling",
            "atmospheric",
            "instrumental",
            "rain",
            "psychedelic",
            "progressive",
            "mysterious",
            "suite",
            "rhythmic"
        ],
        "externalLinks": {
            "bandcamp": "https://steeltippeddove.bandcamp.com/album/inside-outside-inside-outside"
        }
    },
    {
        "albumArt": "https:",
        "position": 11,
        "title": "Punk Goes Drill+**",
        "artist": "Polo Perks",
        "releaseDate": {
            "month": "March",
            "date": 5,
            "year": 2021
        },
        "avgRating": 3.85,
        "ratings": 29,
        "reviews": 2,
        "primaryGenres": [
            "Drill",
            "Trap",
            "East Coast Hip Hop",
            "UK Drill"
        ],
        "secondaryGenres": [
            "Gangsta Rap"
        ],
        "descriptors": [
            "drugs",
            "crime",
            "quirky",
            "rhythmic",
            "male vocals",
            "sampling",
            "violence",
            "chaotic",
            "boastful",
            "hedonistic"
        ],
        "externalLinks": {
            "spotify": "https://open.spotify.com/album/6dW7OisummbH3lC5YSZfpR"
        }
    },
    {
        "albumArt": "https:",
        "position": 12,
        "title": "The Archetype",
        "artist": "Guilherme Nunes",
        "releaseDate": {
            "month": "March",
            "date": 5,
            "year": 2021
        },
        "avgRating": 3.77,
        "ratings": 38,
        "reviews": 4,
        "primaryGenres": [
            "Indie Rock"
        ],
        "secondaryGenres": [
            "Post-Rock",
            "Dream Pop"
        ],
        "descriptors": [
            "noisy",
            "melancholic",
            "atmospheric",
            "male vocals",
            "cold",
            "introspective",
            "dark",
            "cryptic",
            "anxious",
            "passionate"
        ],
        "externalLinks": {
            "appleMusic": "https://geo.music.apple.com/us/album/the-archetype/1556514302?mt=1&app=music&at=10l59k&ct=10l59k",
            "bandcamp": "https://music-guilherme-nunes.bandcamp.com/album/the-archetype",
            "spotify": "https://open.spotify.com/album/3jCpPhRT0lOaOEe4FwnwyL"
        }
    },
    {
        "albumArt": "https:",
        "position": 13,
        "title": "Interstice",
        "artist": "Knoll",
        "releaseDate": {
            "month": "February",
            "date": 26,
            "year": 2021
        },
        "avgRating": 3.57,
        "ratings": 382,
        "reviews": 6,
        "primaryGenres": [
            "Grindcore"
        ],
        "secondaryGenres": [
            "Deathgrind",
            "Noise",
            "Mathcore"
        ],
        "descriptors": [
            "heavy",
            "dissonant",
            "angry",
            "manic",
            "male vocals",
            "dark",
            "noisy",
            "chaotic",
            "ominous"
        ],
        "externalLinks": {
            "appleMusic": "https://geo.music.apple.com/us/album/interstice/1538700822?mt=1&app=music&at=10l59k&ct=10l59k",
            "bandcamp": "https://knollvhs.bandcamp.com/album/interstice-2",
            "spotify": "https://open.spotify.com/album/6UKXm1UJNFttknobiabdNy",
            "youtube": "https://www.youtube.com/watch?v=92TjD7Z6lkg"
        }
    },
    {
        "albumArt": "https:",
        "position": 14,
        "title": "Vivre encore",
        "artist": "LOREM IPSUM",
        "releaseDate": {
            "month": "January",
            "date": 28,
            "year": 2021
        },
        "avgRating": 3.57,
        "ratings": 312,
        "reviews": 12,
        "primaryGenres": [
            "Chamber Music",
            "Screamo",
            "Avant-Folk"
        ],
        "secondaryGenres": [
            "Chamber Folk",
            "Baroque Music",
            "Modern Classical"
        ],
        "descriptors": [
            "avant-garde",
            "passionate",
            "concept album",
            "rhythmic",
            "progressive",
            "male vocals",
            "energetic",
            "lush",
            "atmospheric",
            "depressive"
        ],
        "externalLinks": {
            "bandcamp": "https://loremipsumtrio.bandcamp.com/album/vivre-encore"
        }
    },
    {
        "albumArt": "https:",
        "position": 15,
        "title": "Líquido",
        "artist": "Druida",
        "releaseDate": {
            "month": "March",
            "date": 1,
            "year": 2021
        },
        "avgRating": 3.85,
        "ratings": 26,
        "reviews": null,
        "primaryGenres": [
            "Folktronica",
            "Plunderphonics"
        ],
        "secondaryGenres": [
            "Ambient",
            "Indietronica",
            "Glitch"
        ],
        "descriptors": [
            "peaceful",
            "ethereal",
            "calm",
            "atmospheric",
            "surreal",
            "forest",
            "mysterious",
            "instrumental"
        ],
        "externalLinks": {
            "bandcamp": "https://drruida.bandcamp.com/album/l-quido",
            "youtube": "https://www.youtube.com/watch?v=vk-yvgNhnfE"
        }
    },
    {
        "albumArt": "https:",
        "position": 16,
        "title": "Nieguid duovdagat",
        "artist": "Ánnámáret",
        "releaseDate": {
            "month": "February",
            "date": 5,
            "year": 2021
        },
        "avgRating": 3.76,
        "ratings": 32,
        "reviews": 4,
        "primaryGenres": [
            "Joik"
        ],
        "secondaryGenres": [
            "Folktronica",
            "EAI",
            "Ritual Ambient"
        ],
        "descriptors": [
            "female vocals",
            "ethereal",
            "improvisation",
            "ritualistic",
            "anthemic",
            "winter",
            "atmospheric",
            "soothing",
            "surreal",
            "hypnotic"
        ],
        "externalLinks": {
            "appleMusic": "https://geo.music.apple.com/us/album/nieguid-duovdagat-feat-ilkka-heinonen-turkka-inkil%C3%A4/1548080939?mt=1&app=music&at=10l59k&ct=10l59k",
            "spotify": "https://open.spotify.com/album/08lxS9r1PBTpF8zKL5I3ok"
        }
    },
    {
        "albumArt": "https:",
        "position": 17,
        "title": "Calvaire",
        "artist": "Ferriterium",
        "releaseDate": {
            "month": "January",
            "date": 16,
            "year": 2021
        },
        "avgRating": 3.55,
        "ratings": 451,
        "reviews": 5,
        "primaryGenres": [
            "Black Metal"
        ],
        "secondaryGenres": [
            "Melodic Black Metal"
        ],
        "descriptors": [
            "male vocals",
            "passionate",
            "melodic",
            "energetic",
            "dark",
            "infernal"
        ],
        "externalLinks": {
            "bandcamp": "https://epicturalproduction.bandcamp.com/album/calvaire",
            "youtube": "https://www.youtube.com/watch?v=Y3WD7Jlawno"
        }
    },
    {
        "albumArt": "https:",
        "position": 18,
        "title": "Forever in Your Heart",
        "artist": "Black Dresses",
        "releaseDate": {
            "month": "February",
            "date": 14,
            "year": 2021
        },
        "avgRating": 3.48,
        "ratings": null,
        "reviews": 30,
        "primaryGenres": [
            "Electro-Industrial",
            "Industrial Rock"
        ],
        "secondaryGenres": [
            "Industrial Metal",
            "Electroclash",
            "Glitch Pop"
        ],
        "descriptors": [
            "female vocals",
            "noisy",
            "aggressive",
            "LGBT",
            "mechanical",
            "raw",
            "dissonant",
            "dark",
            "ominous",
            "heavy"
        ],
        "externalLinks": {
            "bandcamp": "https://blackdresses.bandcamp.com/album/forever-in-your-heart",
            "soundcloud": "https://soundcloud.com/dane-jacobs-778776042/sets/black-dresses-forever-in-your-heart",
            "youtube": "https://www.youtube.com/watch?v=83QU6PIsuU8"
        }
    },
    {
        "albumArt": "https:",
        "position": 19,
        "title": "Partitas Part 1: BWV 825, 826, 830",
        "artist": "Evgeni Koroliov",
        "releaseDate": {
            "month": "January",
            "date": 15,
            "year": 2021
        },
        "avgRating": 3.56,
        "ratings": 305,
        "reviews": 2,
        "primaryGenres": [
            "Baroque Music"
        ],
        "secondaryGenres": [
            ""
        ],
        "descriptors": [
            "suite",
            "instrumental",
            "polyphonic",
            "technical",
            "passionate",
            "acoustic",
            "melodic",
            "complex",
            "energetic"
        ],
        "externalLinks": {
            "appleMusic": "https://geo.music.apple.com/us/album/koroliov-series-vol-23-johann-sebastian-bach-partitas/1547267945?mt=1&app=music&at=10l59k&ct=10l59k",
            "spotify": "https://open.spotify.com/album/2uRGF68j2iOvqQD6eWPunS"
        }
    },
    {
        "albumArt": "https:",
        "position": 20,
        "title": "I Became Birds",
        "artist": "Home Is Where",
        "releaseDate": {
            "month": "March",
            "date": 5,
            "year": 2021
        },
        "avgRating": 3.61,
        "ratings": 115,
        "reviews": 4,
        "primaryGenres": [
            "Midwest Emo",
            "Post-Hardcore"
        ],
        "secondaryGenres": [
            "Folk Punk",
            "Screamo"
        ],
        "descriptors": [
            "androgynous vocals",
            "raw",
            "angry",
            "energetic",
            "dense",
            "eclectic",
            "poetic",
            "anxious",
            "warm",
            "cryptic"
        ],
        "externalLinks": {
            "appleMusic": "https://geo.music.apple.com/us/album/i-became-birds-ep/1551854666?mt=1&app=music&at=10l59k&ct=10l59k",
            "bandcamp": "https://homeiswhere.bandcamp.com/album/i-became-birds",
            "spotify": "https://open.spotify.com/album/5PaBlrbwcXN959kiGePXuc"
        }
    },
    {
        "albumArt": "https:",
        "position": 21,
        "title": "冥冥 (Míng Míng)",
        "artist": "Otay:onii",
        "releaseDate": {
            "month": "February",
            "date": 22,
            "year": 2021
        },
        "avgRating": 3.53,
        "ratings": 840,
        "reviews": 12,
        "primaryGenres": [
            "Post-Industrial",
            "Electronic",
            "Art Pop"
        ],
        "secondaryGenres": [
            "Chinese Folk Music",
            "Neoclassical Darkwave",
            "Ambient Pop",
            "Dark Ambient",
            "Drone",
            "Glitch"
        ],
        "descriptors": [
            "female vocals",
            "ominous",
            "avant-garde",
            "surreal",
            "atmospheric",
            "dense",
            "abstract",
            "anxious",
            "nocturnal",
            "repetitive"
        ],
        "externalLinks": {
            "appleMusic": "https://geo.music.apple.com/us/album/ming-ming/1552606886?mt=1&app=music&at=10l59k&ct=10l59k",
            "bandcamp": "https://otayonii.bandcamp.com/album/mingming",
            "spotify": "https://open.spotify.com/album/7dlkAkciSaEjrJyCc5njvU"
        }
    },
    {
        "albumArt": "https:",
        "position": 22,
        "title": "Omega",
        "artist": "Epica",
        "releaseDate": {
            "month": "February",
            "date": 26,
            "year": 2021
        },
        "avgRating": 3.52,
        "ratings": 261,
        "reviews": 7,
        "primaryGenres": [
            "Symphonic Metal"
        ],
        "secondaryGenres": [
            "Progressive Metal",
            "Power Metal",
            "Melodic Death Metal"
        ],
        "descriptors": [
            "orchestral",
            "female vocals",
            "epic",
            "male vocals",
            "energetic",
            "melodic",
            "death",
            "concept album",
            "progressive",
            "uplifting"
        ],
        "externalLinks": {
            "appleMusic": "https://geo.music.apple.com/us/album/omega/1531439598?mt=1&app=music&at=10l59k&ct=10l59k",
            "spotify": "https://open.spotify.com/album/4Hb5cbP4Z9H9G1HavAra4q"
        }
    },
    {
        "albumArt": "https:",
        "position": 23,
        "title": "OH NO",
        "artist": "Xiu Xiu",
        "releaseDate": {
            "month": "March",
            "date": 26,
            "year": 2021
        },
        "avgRating": 3.64,
        "ratings": 64,
        "reviews": null,
        "primaryGenres": [
            "Experimental Rock",
            "Avant-Folk"
        ],
        "secondaryGenres": [
            "Dream Pop",
            "Post-Punk",
            "Noise Pop",
            "Post-Industrial"
        ],
        "descriptors": [
            "noisy",
            "anxious",
            "dark",
            "atmospheric",
            "male vocals",
            "female vocals",
            "ethereal",
            "cryptic"
        ],
        "externalLinks": {
            "appleMusic": "https://geo.music.apple.com/us/album/oh-no/1550396573?mt=1&app=music&at=10l59k&ct=10l59k",
            "bandcamp": "https://xiuxiu.bandcamp.com/album/oh-no"
        }
    },
    {
        "albumArt": "https:",
        "position": 24,
        "title": "The Thule Grimoires",
        "artist": "The Ruins of Beverast",
        "releaseDate": {
            "month": "February",
            "date": 5,
            "year": 2021
        },
        "avgRating": 3.5,
        "ratings": 925,
        "reviews": 4,
        "primaryGenres": [
            "Atmospheric Black Metal",
            "Doom Metal"
        ],
        "secondaryGenres": [
            "Gothic Metal",
            "Death Doom Metal"
        ],
        "descriptors": [
            "dark",
            "cold",
            "atmospheric",
            "heavy",
            "sombre",
            "suspenseful",
            "male vocals",
            "ominous",
            "mysterious",
            "uncommon time signatures"
        ],
        "externalLinks": {
            "appleMusic": "https://geo.music.apple.com/us/album/the-thule-grimoires/1545109012?mt=1&app=music&at=10l59k&ct=10l59k",
            "bandcamp": "https://theruinsofbeverast.bandcamp.com/album/the-thule-grimoires",
            "spotify": "https://open.spotify.com/album/6DoZdbiI54w6OQvW9mgIrr",
            "youtube": "https://www.youtube.com/watch?v=Nd2EOKgxV_M"
        }
    },
    {
        "albumArt": "https:",
        "position": 25,
        "title": "An Overview on Phenomenal Nature",
        "artist": "Cassandra Jenkins",
        "releaseDate": {
            "month": "February",
            "date": 19,
            "year": 2021
        },
        "avgRating": 3.5,
        "ratings": null,
        "reviews": 12,
        "primaryGenres": [
            "Singer/Songwriter"
        ],
        "secondaryGenres": [
            "Chamber Folk",
            "Sophisti-Pop",
            "Ambient Pop",
            "Alt-Country"
        ],
        "descriptors": [
            "atmospheric",
            "mellow",
            "calm",
            "female vocals",
            "nature",
            "existential",
            "introspective",
            "peaceful",
            "soft",
            "warm"
        ],
        "externalLinks": {
            "appleMusic": "https://geo.music.apple.com/us/album/an-overview-on-phenomenal-nature/1539427484?mt=1&app=music&at=10l59k&ct=10l59k",
            "bandcamp": "https://badabingrecords.bandcamp.com/album/an-overview-on-phenomenal-nature",
            "spotify": "https://open.spotify.com/album/1NzOdSkSNmBhhg72KlNcsE",
            "youtube": "https://www.youtube.com/watch?v=Z09xBWNlPpg"
        }
    },
    {
        "albumArt": "https:",
        "position": 26,
        "title": "What Happens After the Death Is Recorded",
        "artist": "DJ Rozwell",
        "releaseDate": {
            "month": "February",
            "date": 23,
            "year": 2021
        },
        "avgRating": 3.54,
        "ratings": 124,
        "reviews": 2,
        "primaryGenres": [
            "Illbient",
            "Wonky",
            "Plunderphonics"
        ],
        "secondaryGenres": [
            "Downtempo",
            "Instrumental Hip Hop",
            "Industrial Hip Hop",
            "Power Noise",
            "Noise Rock"
        ],
        "descriptors": [
            "sampling",
            "surreal",
            "dark",
            "eclectic",
            "rhythmic",
            "raw",
            "noisy",
            "atmospheric",
            "heavy",
            "quirky"
        ],
        "externalLinks": {
            "bandcamp": "https://djrozwell.bandcamp.com/album/what-happens-after-the-death-is-recorded",
            "spotify": "https://open.spotify.com/album/6YRtNx0CitwugojKcNopuQ",
            "youtube": "https://www.youtube.com/watch?v=NoaUZgwSItw"
        }
    },
    {
        "albumArt": "https:",
        "position": 27,
        "title": "Death Fugue",
        "artist": "Anthropophagous",
        "releaseDate": {
            "month": "March",
            "date": 5,
            "year": 2021
        },
        "avgRating": 3.81,
        "ratings": 20,
        "reviews": null,
        "primaryGenres": [
            "Death Metal"
        ],
        "secondaryGenres": [
            ""
        ],
        "descriptors": [
            "raw",
            "dark",
            "death",
            "male vocals",
            "ominous"
        ],
        "externalLinks": {
            "bandcamp": "https://anthropophagous.bandcamp.com/album/death-fugue",
            "spotify": "https://open.spotify.com/album/3uVHKXz08bXmKG4exUsykb",
            "youtube": "https://www.youtube.com/watch?v=xO42q3hb8Rc"
        }
    },
    {
        "albumArt": "https:",
        "position": 28,
        "title": "Through Aureate Void",
        "artist": "Five the Hierophant",
        "releaseDate": {
            "month": "February",
            "date": 26,
            "year": 2021
        },
        "avgRating": 3.52,
        "ratings": 77,
        "reviews": 1,
        "primaryGenres": [
            "Avant-Garde Metal"
        ],
        "secondaryGenres": [
            "Atmospheric Sludge Metal",
            "Dark Jazz"
        ],
        "descriptors": [
            "heavy",
            "sombre",
            "atmospheric",
            "male vocals",
            "dense",
            "dark"
        ],
        "externalLinks": {
            "appleMusic": "https://geo.music.apple.com/us/album/through-aureate-void/1540810235?mt=1&app=music&at=10l59k&ct=10l59k",
            "bandcamp": "https://five-the-hierophant.bandcamp.com/album/through-aureate-void",
            "spotify": "https://open.spotify.com/album/3lCOpnRPgOcgUzvMeeCZIO",
            "youtube": "https://www.youtube.com/watch?v=dnesM3O8wmQ"
        }
    },
    {
        "albumArt": "https:",
        "position": 29,
        "title": "The Golden Pentacle",
        "artist": "Marco Garau's Magic Opera",
        "releaseDate": {
            "month": "February",
            "date": 19,
            "year": 2021
        },
        "avgRating": 3.81,
        "ratings": 17,
        "reviews": 2,
        "primaryGenres": [
            "Power Metal",
            "Symphonic Metal"
        ],
        "secondaryGenres": [
            "Neoclassical Metal",
            "Progressive Metal"
        ],
        "descriptors": [
            "energetic",
            "concept album",
            "male vocals",
            "triumphant",
            "melodic",
            "progressive",
            "epic",
            "rock opera"
        ],
        "externalLinks": {
            "bandcamp": "https://magicopera.bandcamp.com/album/the-golden-pentacle",
            "spotify": "https://open.spotify.com/album/3NwjFL5ZwBKUV7Ax68qpew",
            "youtube": "https://www.youtube.com/watch?v=EuYFigTOMpI"
        }
    },
    {
        "albumArt": "https:",
        "position": 30,
        "title": "Possessed by Evil",
        "artist": "Evil",
        "releaseDate": {
            "month": "February",
            "date": 1,
            "year": 2021
        },
        "avgRating": 3.56,
        "ratings": 74,
        "reviews": 1,
        "primaryGenres": [
            "Thrash Metal",
            "Black Metal"
        ],
        "secondaryGenres": [
            "Speed Metal"
        ],
        "descriptors": [
            "infernal",
            "raw",
            "aggressive",
            "male vocals"
        ],
        "externalLinks": {
            "bandcamp": "https://nuclearwarnowproductions.bandcamp.com/album/possessed-by-evil"
        }
    },
    {
        "albumArt": "https:",
        "position": 31,
        "title": "Xuntas",
        "artist": "Sangre de Muérdago",
        "releaseDate": {
            "month": "January",
            "date": 28,
            "year": 2021
        },
        "avgRating": 3.5,
        "ratings": 201,
        "reviews": 2,
        "primaryGenres": [
            "Dark Folk"
        ],
        "secondaryGenres": [
            "Galician Folk Music",
            "Chamber Folk"
        ],
        "descriptors": [
            "male vocals",
            "melodic",
            "folklore",
            "melancholic",
            "sentimental",
            "autumn",
            "forest",
            "acoustic",
            "calm",
            "pastoral"
        ],
        "externalLinks": {
            "appleMusic": "https://geo.music.apple.com/us/album/xuntas/1537665445?mt=1&app=music&at=10l59k&ct=10l59k",
            "bandcamp": "https://sangredemuerdago.bandcamp.com/album/xuntas",
            "soundcloud": "https://soundcloud.com/sangredemuerdago-music/sets/xuntas",
            "spotify": "https://open.spotify.com/album/01pyFiVfjAxi28LDNofJWG",
            "youtube": "https://www.youtube.com/watch?v=-uEG2H_4KCg"
        }
    },
    {
        "albumArt": "https:",
        "position": 32,
        "title": "Drunk Tank Pink",
        "artist": "Shame",
        "releaseDate": {
            "month": "January",
            "date": 15,
            "year": 2021
        },
        "avgRating": 3.44,
        "ratings": null,
        "reviews": 50,
        "primaryGenres": [
            "Post-Punk",
            "Art Punk"
        ],
        "secondaryGenres": [
            "Post-Hardcore",
            "Dance-Punk"
        ],
        "descriptors": [
            "male vocals",
            "rhythmic",
            "energetic",
            "noisy",
            "aggressive",
            "passionate",
            "anxious",
            "dissonant",
            "alienation",
            "introspective"
        ],
        "externalLinks": {
            "appleMusic": "https://geo.music.apple.com/us/album/drunk-tank-pink/1538884444?mt=1&app=music&at=10l59k&ct=10l59k",
            "bandcamp": "https://shamebanduk.bandcamp.com/album/drunk-tank-pink",
            "soundcloud": "https://soundcloud.com/shame75842/sets/drunk-tank-pink-2",
            "spotify": "https://open.spotify.com/album/7hl54HF6Nykh5IDrbqhiJX",
            "youtube": "https://www.youtube.com/watch?v=MEAHUyiaQDY"
        }
    },
    {
        "albumArt": "https:",
        "position": 33,
        "title": "Death & the Magician",
        "artist": "Muggs x Rome StreetzDJ MuggsRome Streetz",
        "releaseDate": {
            "month": "February",
            "date": 22,
            "year": 2021
        },
        "avgRating": 3.5,
        "ratings": 228,
        "reviews": 2,
        "primaryGenres": [
            "East Coast Hip Hop",
            "Gangsta Rap",
            "Boom Bap"
        ],
        "secondaryGenres": [
            "Hardcore Hip Hop"
        ],
        "descriptors": [
            "crime",
            "sampling",
            "dark",
            "urban",
            "drugs",
            "aggressive",
            "boastful",
            "male vocals"
        ],
        "externalLinks": {
            "appleMusic": "https://geo.music.apple.com/us/album/death-the-magician/1553016009?mt=1&app=music&at=10l59k&ct=10l59k",
            "soundcloud": "https://soundcloud.com/dj-muggs-official/sets/death-the-magician",
            "spotify": "https://open.spotify.com/album/5DufTGQ0fIS3cJ6HOFCbbx",
            "youtube": "https://www.youtube.com/watch?v=vpTX8pVhq_U"
        }
    },
    {
        "albumArt": "https:",
        "position": 34,
        "title": "Psychic Secretions",
        "artist": "StarGazer",
        "releaseDate": {
            "month": "2021",
            "date": null,
            "year": 0
        },
        "avgRating": 3.49,
        "ratings": 234,
        "reviews": 5,
        "primaryGenres": [
            "Technical Death Metal"
        ],
        "secondaryGenres": [
            "Progressive Metal",
            "Black Metal"
        ],
        "descriptors": [
            "technical",
            "dark",
            "male vocals",
            "atmospheric",
            "occult",
            "mysterious"
        ],
        "externalLinks": {
            "bandcamp": "https://stargazeraustralia.bandcamp.com/album/psychic-secretions",
            "youtube": "https://www.youtube.com/watch?v=iXenzmFVF-M"
        }
    },
    {
        "albumArt": "https:",
        "position": 35,
        "title": "Niratias",
        "artist": "Chevelle",
        "releaseDate": {
            "month": "March",
            "date": 5,
            "year": 2021
        },
        "avgRating": 3.51,
        "ratings": 175,
        "reviews": 6,
        "primaryGenres": [
            "Alternative Metal"
        ],
        "secondaryGenres": [
            "Progressive Metal",
            "Alternative Rock"
        ],
        "descriptors": [
            "male vocals",
            "space",
            "melodic",
            "science fiction",
            "heavy",
            "epic",
            "cryptic",
            "apocalyptic",
            "concept album"
        ],
        "externalLinks": {
            "appleMusic": "https://geo.music.apple.com/us/album/niratias/1545068576?mt=1&app=music&at=10l59k&ct=10l59k",
            "spotify": "https://open.spotify.com/album/3OFNdoIt29176cAfAoSUfH"
        }
    },
    {
        "albumArt": "https:",
        "position": 36,
        "title": "Über den Sternen",
        "artist": "Empyrium",
        "releaseDate": {
            "month": "February",
            "date": 26,
            "year": 2021
        },
        "avgRating": 3.48,
        "ratings": 204,
        "reviews": 2,
        "primaryGenres": [
            "Dark Folk",
            "Folk Metal"
        ],
        "secondaryGenres": [
            "Neoclassical Darkwave",
            "Doom Metal",
            "Atmospheric Black Metal"
        ],
        "descriptors": [
            "dark",
            "melancholic",
            "atmospheric",
            "nature",
            "male vocals",
            "sombre"
        ],
        "externalLinks": {
            "appleMusic": "https://geo.music.apple.com/us/album/%C3%BCber-den-sternen/1542693960?mt=1&app=music&at=10l59k&ct=10l59k",
            "bandcamp": "https://empyrium.bandcamp.com/album/ber-den-sternen",
            "spotify": "https://open.spotify.com/album/3F4adkiHd687S10c2K9wjF"
        }
    },
    {
        "albumArt": "https:",
        "position": 37,
        "title": "Running Games",
        "artist": "Joel Hoekstra's 13",
        "releaseDate": {
            "month": "February",
            "date": 12,
            "year": 2021
        },
        "avgRating": 3.66,
        "ratings": 35,
        "reviews": 2,
        "primaryGenres": [
            "Hard Rock"
        ],
        "secondaryGenres": [
            ""
        ],
        "descriptors": [
            ""
        ],
        "externalLinks": {
            "spotify": "https://open.spotify.com/album/4SHxPXoH9nYuMX9GTStiQO"
        }
    },
    {
        "albumArt": "https:",
        "position": 38,
        "title": "Forhist",
        "artist": "Forhist",
        "releaseDate": {
            "month": "February",
            "date": 26,
            "year": 2021
        },
        "avgRating": 3.52,
        "ratings": 115,
        "reviews": 1,
        "primaryGenres": [
            "Atmospheric Black Metal"
        ],
        "secondaryGenres": [
            "Melodic Black Metal"
        ],
        "descriptors": [
            "dark",
            "occult",
            "atmospheric",
            "aggressive",
            "male vocals",
            "cold"
        ],
        "externalLinks": {
            "appleMusic": "https://geo.music.apple.com/us/album/forhist/1547998686?mt=1&app=music&at=10l59k&ct=10l59k",
            "bandcamp": "https://blutausnord.bandcamp.com/album/forhist",
            "spotify": "https://open.spotify.com/album/18SjlBmKXveM7qrNx8tS9y",
            "youtube": "https://www.youtube.com/watch?v=9KD0KnNDLkw"
        }
    },
    {
        "albumArt": "https:",
        "position": 39,
        "title": "Crime and Punishment",
        "artist": "Regional Justice Center",
        "releaseDate": {
            "month": "March",
            "date": 5,
            "year": 2021
        },
        "avgRating": 3.57,
        "ratings": 72,
        "reviews": 1,
        "primaryGenres": [
            "Powerviolence"
        ],
        "secondaryGenres": [
            ""
        ],
        "descriptors": [
            "male vocals",
            "chaotic",
            "aggressive",
            "manic",
            "angry",
            "technical",
            "violence"
        ],
        "externalLinks": {
            "appleMusic": "https://geo.music.apple.com/us/album/crime-and-punishment/1545227526?mt=1&app=music&at=10l59k&ct=10l59k",
            "bandcamp": "https://regionaljusticecenter.bandcamp.com/album/crime-and-punishment",
            "spotify": "https://open.spotify.com/album/6cXkDr4QGlRq4kWwAkGkLm",
            "youtube": "https://www.youtube.com/watch?v=8Do3TA6kAEk"
        }
    },
    {
        "albumArt": "https:",
        "position": 40,
        "title": "Access All Worlds",
        "artist": "Iotunn",
        "releaseDate": {
            "month": "February",
            "date": 26,
            "year": 2021
        },
        "avgRating": 3.49,
        "ratings": 113,
        "reviews": 1,
        "primaryGenres": [
            "Progressive Metal"
        ],
        "secondaryGenres": [
            "Melodic Death Metal",
            "Power Metal"
        ],
        "descriptors": [
            "melodic",
            "epic",
            "male vocals",
            "space",
            "concept album",
            "progressive",
            "dense",
            "introspective",
            "uplifting",
            "technical"
        ],
        "externalLinks": {
            "bandcamp": "https://iotunn.bandcamp.com/album/access-all-worlds",
            "spotify": "https://open.spotify.com/album/0n2lmzkIfpLnZa3T1YaFry",
            "youtube": "https://www.youtube.com/watch?v=CPw4mW7UwCA"
        }
    }
]